<PAMDataset>
  <PAMRasterBand band="1">
    <Histograms>
      <HistItem>
        <HistMin>0.5026455026455027</HistMin>
        <HistMax>189.4973544973545</HistMax>
        <BucketCount>189</BucketCount>
        <IncludeOutOfRange>0</IncludeOutOfRange>
        <Approximate>0</Approximate>
        <HistCounts>42082|139|148|153|121|132|145|136|137|135|156|137|152|169|165|144|155|148|164|143|151|145|136|148|137|141|138|146|153|140|137|158|156|147|136|161|132|147|154|133|167|139|152|148|150|137|130|131|144|161|142|144|161|178|140|169|151|146|123|138|163|148|164|171|159|148|169|160|156|171|153|142|176|161|153|167|158|184|166|148|142|178|152|148|173|155|160|161|163|183|170|155|157|157|165|178|202|166|163|148|154|170|177|145|193|157|191|181|171|183|178|170|191|170|182|163|179|191|198|160|175|188|186|177|171|197|168|215|195|191|200|176|220|219|179|195|211|215|221|222|215|243|214|230|206|262|224|216|250|231|250|241|274|259|232|286|279|255|249|286|262|302|313|320|334|331|301|370|358|367|421|359|452|467|526|554|642|683|961|1655|1059|6|7|0|6|0|0|0|2</HistCounts>
      </HistItem>
    </Histograms>
    <Metadata>
      <MDI key="STATISTICS_MAXIMUM">189</MDI>
      <MDI key="STATISTICS_MEAN">54.578289032834</MDI>
      <MDI key="STATISTICS_MINIMUM">1</MDI>
      <MDI key="STATISTICS_STDDEV">67.849099788978</MDI>
    </Metadata>
  </PAMRasterBand>
</PAMDataset>
